<annotation><filename>00000595</filename><size><width>1920</width><height>1080</height></size><class>person</class><views><name>person</name><pose>NA</pose><truncated>0</truncated><difficult>0</difficult><bndbox><xmin>870</xmin><ymin>111</ymin><xmax>907</xmax><ymax>253</ymax></bndbox></views><views><name>person</name><pose>NA</pose><truncated>0</truncated><difficult>0</difficult><bndbox><xmin>1458</xmin><ymin>130</ymin><xmax>1505</xmax><ymax>277</ymax></bndbox></views><views><name>person</name><pose>NA</pose><truncated>0</truncated><difficult>0</difficult><bndbox><xmin>1439</xmin><ymin>116</ymin><xmax>1479</xmax><ymax>243</ymax></bndbox></views><views><name>person</name><pose>NA</pose><truncated>0</truncated><difficult>0</difficult><bndbox><xmin>1479</xmin><ymin>124</ymin><xmax>1523</xmax><ymax>262</ymax></bndbox></views><views><name>person</name><pose>NA</pose><truncated>0</truncated><difficult>0</difficult><bndbox><xmin>1428</xmin><ymin>108</ymin><xmax>1464</xmax><ymax>221</ymax></bndbox></views><views><name>person</name><pose>NA</pose><truncated>0</truncated><difficult>0</difficult><bndbox><xmin>1567</xmin><ymin>121</ymin><xmax>1609</xmax><ymax>249</ymax></bndbox></views><views><name>person</name><pose>NA</pose><truncated>0</truncated><difficult>0</difficult><bndbox><xmin>-1</xmin><ymin>-1</ymin><xmax>-1</xmax><ymax>-1</ymax></bndbox></views><views><name>person</name><pose>NA</pose><truncated>0</truncated><difficult>0</difficult><bndbox><xmin>1507</xmin><ymin>120</ymin><xmax>1548</xmax><ymax>249</ymax></bndbox></views><views><name>person</name><pose>NA</pose><truncated>0</truncated><difficult>0</difficult><bndbox><xmin>1061</xmin><ymin>119</ymin><xmax>1102</xmax><ymax>266</ymax></bndbox></views><views><name>person</name><pose>NA</pose><truncated>0</truncated><difficult>0</difficult><bndbox><xmin>1288</xmin><ymin>131</ymin><xmax>1335</xmax><ymax>287</ymax></bndbox></views><views><name>person</name><pose>NA</pose><truncated>0</truncated><difficult>0</difficult><bndbox><xmin>1738</xmin><ymin>165</ymin><xmax>1804</xmax><ymax>356</ymax></bndbox></views><views><name>person</name><pose>NA</pose><truncated>0</truncated><difficult>0</difficult><bndbox><xmin>1664</xmin><ymin>123</ymin><xmax>1707</xmax><ymax>252</ymax></bndbox></views><views><name>person</name><pose>NA</pose><truncated>0</truncated><difficult>0</difficult><bndbox><xmin>844</xmin><ymin>339</ymin><xmax>979</xmax><ymax>831</ymax></bndbox></views><views><name>person</name><pose>NA</pose><truncated>0</truncated><difficult>0</difficult><bndbox><xmin>1258</xmin><ymin>173</ymin><xmax>1325</xmax><ymax>396</ymax></bndbox></views><views><name>person</name><pose>NA</pose><truncated>0</truncated><difficult>0</difficult><bndbox><xmin>1088</xmin><ymin>371</ymin><xmax>1247</xmax><ymax>902</ymax></bndbox></views><views><name>person</name><pose>NA</pose><truncated>0</truncated><difficult>0</difficult><bndbox><xmin>1535</xmin><ymin>132</ymin><xmax>1583</xmax><ymax>280</ymax></bndbox></views><views><name>person</name><pose>NA</pose><truncated>0</truncated><difficult>0</difficult><bndbox><xmin>1684</xmin><ymin>187</ymin><xmax>1762</xmax><ymax>414</ymax></bndbox></views><views><name>person</name><pose>NA</pose><truncated>0</truncated><difficult>0</difficult><bndbox><xmin>1519</xmin><ymin>125</ymin><xmax>1563</xmax><ymax>262</ymax></bndbox></views><views><name>person</name><pose>NA</pose><truncated>0</truncated><difficult>0</difficult><bndbox><xmin>1640</xmin><ymin>174</ymin><xmax>1710</xmax><ymax>383</ymax></bndbox></views><views><name>person</name><pose>NA</pose><truncated>0</truncated><difficult>0</difficult><bndbox><xmin>198</xmin><ymin>149</ymin><xmax>276</xmax><ymax>379</ymax></bndbox></views></annotation>