<annotation><size><width>1920</width><height>1080</height></size><personid>7</personid><positionid>12179</positionid><views><viewnum>0</viewnum><bndbox><xmin>-1</xmin><ymin>-1</ymin><xmax>-1</xmax><ymax>-1</ymax></bndbox></views><personid>3</personid><positionid>82241</positionid><views><viewnum>0</viewnum><bndbox><xmin>-1</xmin><ymin>-1</ymin><xmax>-1</xmax><ymax>-1</ymax></bndbox></views><personid>626</personid><positionid>475412</positionid><views><viewnum>0</viewnum><bndbox><xmin>1254</xmin><ymin>122</ymin><xmax>1296</xmax><ymax>265</ymax></bndbox></views><personid>116</personid><positionid>445312</positionid><views><viewnum>0</viewnum><bndbox><xmin>1513</xmin><ymin>142</ymin><xmax>1566</xmax><ymax>307</ymax></bndbox></views><personid>23</personid><positionid>463077</positionid><views><viewnum>0</viewnum><bndbox><xmin>1540</xmin><ymin>139</ymin><xmax>1591</xmax><ymax>298</ymax></bndbox></views><personid>1</personid><positionid>353441</positionid><views><viewnum>0</viewnum><bndbox><xmin>926</xmin><ymin>138</ymin><xmax>975</xmax><ymax>321</ymax></bndbox></views><personid>21</personid><positionid>473676</positionid><views><viewnum>0</viewnum><bndbox><xmin>1636</xmin><ymin>142</ymin><xmax>1689</xmax><ymax>300</ymax></bndbox></views><personid>24</personid><positionid>519759</positionid><views><viewnum>0</viewnum><bndbox><xmin>1668</xmin><ymin>133</ymin><xmax>1717</xmax><ymax>277</ymax></bndbox></views><personid>0</personid><positionid>366391</positionid><views><viewnum>0</viewnum><bndbox><xmin>937</xmin><ymin>134</ymin><xmax>984</xmax><ymax>310</ymax></bndbox></views><personid>16</personid><positionid>172349</positionid><views><viewnum>0</viewnum><bndbox><xmin>-1</xmin><ymin>-1</ymin><xmax>-1</xmax><ymax>-1</ymax></bndbox></views><personid>20</personid><positionid>598724</positionid><views><viewnum>0</viewnum><bndbox><xmin>1310</xmin><ymin>104</ymin><xmax>1344</xmax><ymax>217</ymax></bndbox></views><personid>5</personid><positionid>523860</positionid><views><viewnum>0</viewnum><bndbox><xmin>1257</xmin><ymin>113</ymin><xmax>1295</xmax><ymax>241</ymax></bndbox></views><personid>18</personid><positionid>275084</positionid><views><viewnum>0</viewnum><bndbox><xmin>399</xmin><ymin>141</ymin><xmax>462</xmax><ymax>349</ymax></bndbox></views><personid>4</personid><positionid>78908</positionid><views><viewnum>0</viewnum><bndbox><xmin>-1</xmin><ymin>-1</ymin><xmax>-1</xmax><ymax>-1</ymax></bndbox></views><personid>22</personid><positionid>602097</positionid><views><viewnum>0</viewnum><bndbox><xmin>1333</xmin><ymin>105</ymin><xmax>1367</xmax><ymax>217</ymax></bndbox></views><personid>6</personid><positionid>153469</positionid><views><viewnum>0</viewnum><bndbox><xmin>668</xmin><ymin>336</ymin><xmax>800</xmax><ymax>832</ymax></bndbox></views><personid>30</personid><positionid>600211</positionid><views><viewnum>0</viewnum><bndbox><xmin>1383</xmin><ymin>107</ymin><xmax>1419</xmax><ymax>222</ymax></bndbox></views><personid>168</personid><positionid>470364</positionid><views><viewnum>0</viewnum><bndbox><xmin>1749</xmin><ymin>148</ymin><xmax>1806</xmax><ymax>312</ymax></bndbox></views><personid>13</personid><positionid>464086</positionid><views><viewnum>0</viewnum><bndbox><xmin>1654</xmin><ymin>145</ymin><xmax>1709</xmax><ymax>307</ymax></bndbox></views><personid>26</personid><positionid>129634</positionid><views><viewnum>0</viewnum><bndbox><xmin>-1</xmin><ymin>-1</ymin><xmax>-1</xmax><ymax>-1</ymax></bndbox></views><personid>12</personid><positionid>455420</positionid><views><viewnum>0</viewnum><bndbox><xmin>1587</xmin><ymin>143</ymin><xmax>1641</xmax><ymax>307</ymax></bndbox></views><personid>383</personid><positionid>484078</positionid><views><viewnum>0</viewnum><bndbox><xmin>1314</xmin><ymin>123</ymin><xmax>1357</xmax><ymax>265</ymax></bndbox></views><personid>43</personid><positionid>471175</positionid><views><viewnum>0</viewnum><bndbox><xmin>1413</xmin><ymin>131</ymin><xmax>1460</xmax><ymax>281</ymax></bndbox></views></annotation>