<annotation><size><width>1920</width><height>1080</height></size><personid>147</personid><positionid>240033</positionid><views><viewnum>0</viewnum><bndbox><xmin>196</xmin><ymin>149</ymin><xmax>274</xmax><ymax>379</ymax></bndbox></views><personid>115</personid><positionid>322399</positionid><views><viewnum>0</viewnum><bndbox><xmin>1255</xmin><ymin>173</ymin><xmax>1322</xmax><ymax>396</ymax></bndbox></views><personid>413</personid><positionid>195777</positionid><views><viewnum>0</viewnum><bndbox><xmin>1312</xmin><ymin>305</ymin><xmax>1446</xmax><ymax>728</ymax></bndbox></views><personid>472</personid><positionid>496201</positionid><views><viewnum>0</viewnum><bndbox><xmin>1574</xmin><ymin>133</ymin><xmax>1622</xmax><ymax>281</ymax></bndbox></views><personid>16</personid><positionid>181021</positionid><views><viewnum>0</viewnum><bndbox><xmin>-1</xmin><ymin>-1</ymin><xmax>-1</xmax><ymax>-1</ymax></bndbox></views><personid>144</personid><positionid>609356</positionid><views><viewnum>0</viewnum><bndbox><xmin>1430</xmin><ymin>108</ymin><xmax>1466</xmax><ymax>222</ymax></bndbox></views><personid>196</personid><positionid>476264</positionid><views><viewnum>0</viewnum><bndbox><xmin>1063</xmin><ymin>112</ymin><xmax>1100</xmax><ymax>247</ymax></bndbox></views><personid>323</personid><positionid>573405</positionid><views><viewnum>0</viewnum><bndbox><xmin>1484</xmin><ymin>116</ymin><xmax>1523</xmax><ymax>239</ymax></bndbox></views><personid>562</personid><positionid>198237</positionid><views><viewnum>0</viewnum><bndbox><xmin>1697</xmin><ymin>338</ymin><xmax>1860</xmax><ymax>796</ymax></bndbox></views><personid>559</personid><positionid>384479</positionid><views><viewnum>0</viewnum><bndbox><xmin>1820</xmin><ymin>179</ymin><xmax>1894</xmax><ymax>389</ymax></bndbox></views><personid>468</personid><positionid>628015</positionid><views><viewnum>0</viewnum><bndbox><xmin>1353</xmin><ymin>102</ymin><xmax>1385</xmax><ymax>210</ymax></bndbox></views><personid>399</personid><positionid>619347</positionid><views><viewnum>0</viewnum><bndbox><xmin>1304</xmin><ymin>101</ymin><xmax>1337</xmax><ymax>210</ymax></bndbox></views><personid>305</personid><positionid>506202</positionid><views><viewnum>0</viewnum><bndbox><xmin>1422</xmin><ymin>124</ymin><xmax>1466</xmax><ymax>263</ymax></bndbox></views><personid>563</personid><positionid>363348</positionid><views><viewnum>0</viewnum><bndbox><xmin>1776</xmin><ymin>185</ymin><xmax>1854</xmax><ymax>407</ymax></bndbox></views><personid>471</personid><positionid>451078</positionid><views><viewnum>0</viewnum><bndbox><xmin>1532</xmin><ymin>142</ymin><xmax>1585</xmax><ymax>305</ymax></bndbox></views><personid>134</personid><positionid>406645</positionid><views><viewnum>0</viewnum><bndbox><xmin>899</xmin><ymin>119</ymin><xmax>939</xmax><ymax>273</ymax></bndbox></views><personid>526</personid><positionid>477926</positionid><views><viewnum>0</viewnum><bndbox><xmin>1485</xmin><ymin>133</ymin><xmax>1533</xmax><ymax>284</ymax></bndbox></views><personid>418</personid><positionid>505313</positionid><views><viewnum>0</viewnum><bndbox><xmin>1563</xmin><ymin>131</ymin><xmax>1610</xmax><ymax>276</ymax></bndbox></views><personid>584</personid><positionid>524103</positionid><views><viewnum>0</viewnum><bndbox><xmin>1721</xmin><ymin>135</ymin><xmax>1771</xmax><ymax>279</ymax></bndbox></views><personid>160</personid><positionid>485580</positionid><views><viewnum>0</viewnum><bndbox><xmin>1438</xmin><ymin>129</ymin><xmax>1484</xmax><ymax>275</ymax></bndbox></views><personid>467</personid><positionid>522615</positionid><views><viewnum>0</viewnum><bndbox><xmin>1620</xmin><ymin>130</ymin><xmax>1666</xmax><ymax>272</ymax></bndbox></views><personid>161</personid><positionid>399898</positionid><views><viewnum>0</viewnum><bndbox><xmin>835</xmin><ymin>118</ymin><xmax>874</xmax><ymax>272</ymax></bndbox></views><personid>273</personid><positionid>462154</positionid><views><viewnum>0</viewnum><bndbox><xmin>1625</xmin><ymin>144</ymin><xmax>1679</xmax><ymax>306</ymax></bndbox></views></annotation>