<annotation><size><width>1920</width><height>1080</height></size><personid>65</personid><positionid>482771</positionid><views><viewnum>0</viewnum><bndbox><xmin>1586</xmin><ymin>137</ymin><xmax>1636</xmax><ymax>290</ymax></bndbox></views><personid>62</personid><positionid>491004</positionid><views><viewnum>0</viewnum><bndbox><xmin>1757</xmin><ymin>144</ymin><xmax>1811</xmax><ymax>300</ymax></bndbox></views><personid>592</personid><positionid>422739</positionid><views><viewnum>0</viewnum><bndbox><xmin>1460</xmin><ymin>146</ymin><xmax>1514</xmax><ymax>318</ymax></bndbox></views><personid>63</personid><positionid>208663</positionid><views><viewnum>0</viewnum><bndbox><xmin>994</xmin><ymin>252</ymin><xmax>1094</xmax><ymax>608</ymax></bndbox></views><personid>67</personid><positionid>239433</positionid><views><viewnum>0</viewnum><bndbox><xmin>1327</xmin><ymin>242</ymin><xmax>1429</xmax><ymax>568</ymax></bndbox></views><personid>559</personid><positionid>255122</positionid><views><viewnum>0</viewnum><bndbox><xmin>825</xmin><ymin>186</ymin><xmax>893</xmax><ymax>448</ymax></bndbox></views><personid>241</personid><positionid>399751</positionid><views><viewnum>0</viewnum><bndbox><xmin>1569</xmin><ymin>159</ymin><xmax>1631</xmax><ymax>348</ymax></bndbox></views><personid>68</personid><positionid>403657</positionid><views><viewnum>0</viewnum><bndbox><xmin>1758</xmin><ymin>168</ymin><xmax>1826</xmax><ymax>364</ymax></bndbox></views><personid>617</personid><positionid>313918</positionid><views><viewnum>0</viewnum><bndbox><xmin>1792</xmin><ymin>213</ymin><xmax>1885</xmax><ymax>477</ymax></bndbox></views><personid>115</personid><positionid>326242</positionid><views><viewnum>0</viewnum><bndbox><xmin>1272</xmin><ymin>172</ymin><xmax>1339</xmax><ymax>393</ymax></bndbox></views><personid>572</personid><positionid>132356</positionid><views><viewnum>0</viewnum><bndbox><xmin>477</xmin><ymin>395</ymin><xmax>649</xmax><ymax>984</ymax></bndbox></views><personid>563</personid><positionid>272908</positionid><views><viewnum>0</viewnum><bndbox><xmin>970</xmin><ymin>183</ymin><xmax>1039</xmax><ymax>435</ymax></bndbox></views><personid>506</personid><positionid>614203</positionid><views><viewnum>0</viewnum><bndbox><xmin>1509</xmin><ymin>111</ymin><xmax>1545</xmax><ymax>226</ymax></bndbox></views><personid>177</personid><positionid>273425</positionid><views><viewnum>0</viewnum><bndbox><xmin>1090</xmin><ymin>192</ymin><xmax>1164</xmax><ymax>452</ymax></bndbox></views><personid>353</personid><positionid>240266</positionid><views><viewnum>0</viewnum><bndbox><xmin>840</xmin><ymin>201</ymin><xmax>915</xmax><ymax>484</ymax></bndbox></views><personid>147</personid><positionid>231387</positionid><views><viewnum>0</viewnum><bndbox><xmin>132</xmin><ymin>151</ymin><xmax>214</xmax><ymax>386</ymax></bndbox></views><personid>64</personid><positionid>212962</positionid><views><viewnum>0</viewnum><bndbox><xmin>924</xmin><ymin>239</ymin><xmax>1017</xmax><ymax>579</ymax></bndbox></views><personid>16</personid><positionid>176747</positionid><views><viewnum>0</viewnum><bndbox><xmin>-75</xmin><ymin>195</ymin><xmax>44</xmax><ymax>507</ymax></bndbox></views><personid>1148</personid><positionid>609367</positionid><views><viewnum>0</viewnum><bndbox><xmin>1447</xmin><ymin>109</ymin><xmax>1483</xmax><ymax>223</ymax></bndbox></views><personid>245</personid><positionid>491339</positionid><views><viewnum>0</viewnum><bndbox><xmin>1441</xmin><ymin>128</ymin><xmax>1487</xmax><ymax>272</ymax></bndbox></views><personid>616</personid><positionid>623309</positionid><views><viewnum>0</viewnum><bndbox><xmin>1492</xmin><ymin>109</ymin><xmax>1528</xmax><ymax>222</ymax></bndbox></views><personid>198</personid><positionid>256124</positionid><views><viewnum>0</viewnum><bndbox><xmin>963</xmin><ymin>196</ymin><xmax>1037</xmax><ymax>468</ymax></bndbox></views><personid>196</personid><positionid>305985</positionid><views><viewnum>0</viewnum><bndbox><xmin>951</xmin><ymin>161</ymin><xmax>1010</xmax><ymax>379</ymax></bndbox></views><personid>66</personid><positionid>130466</positionid><views><viewnum>0</viewnum><bndbox><xmin>674</xmin><ymin>435</ymin><xmax>848</xmax><ymax>1074</ymax></bndbox></views><personid>224</personid><positionid>129580</positionid><views><viewnum>0</viewnum><bndbox><xmin>1330</xmin><ymin>550</ymin><xmax>1591</xmax><ymax>1326</ymax></bndbox></views></annotation>