<annotation><size><width>1920</width><height>1080</height></size><personid>74</personid><positionid>651056</positionid><views><viewnum>0</viewnum><bndbox><xmin>1373</xmin><ymin>101</ymin><xmax>1405</xmax><ymax>205</ymax></bndbox></views><personid>77</personid><positionid>525882</positionid><views><viewnum>0</viewnum><bndbox><xmin>1440</xmin><ymin>121</ymin><xmax>1482</xmax><ymax>256</ymax></bndbox></views><personid>80</personid><positionid>319071</positionid><views><viewnum>0</viewnum><bndbox><xmin>1346</xmin><ymin>180</ymin><xmax>1418</xmax><ymax>412</ymax></bndbox></views><personid>78</personid><positionid>528787</positionid><views><viewnum>0</viewnum><bndbox><xmin>1490</xmin><ymin>123</ymin><xmax>1533</xmax><ymax>258</ymax></bndbox></views><personid>79</personid><positionid>536485</positionid><views><viewnum>0</viewnum><bndbox><xmin>1530</xmin><ymin>124</ymin><xmax>1573</xmax><ymax>258</ymax></bndbox></views><personid>147</personid><positionid>216978</positionid><views><viewnum>0</viewnum><bndbox><xmin>20</xmin><ymin>154</ymin><xmax>110</xmax><ymax>399</ymax></bndbox></views><personid>198</personid><positionid>255167</positionid><views><viewnum>0</viewnum><bndbox><xmin>969</xmin><ymin>197</ymin><xmax>1045</xmax><ymax>471</ymax></bndbox></views><personid>559</personid><positionid>255121</positionid><views><viewnum>0</viewnum><bndbox><xmin>822</xmin><ymin>186</ymin><xmax>890</xmax><ymax>448</ymax></bndbox></views><personid>196</personid><positionid>305502</positionid><views><viewnum>0</viewnum><bndbox><xmin>942</xmin><ymin>161</ymin><xmax>1001</xmax><ymax>379</ymax></bndbox></views><personid>16</personid><positionid>174345</positionid><views><viewnum>0</viewnum><bndbox><xmin>-102</xmin><ymin>196</ymin><xmax>19</xmax><ymax>511</ymax></bndbox></views><personid>76</personid><positionid>634790</positionid><views><viewnum>0</viewnum><bndbox><xmin>1440</xmin><ymin>105</ymin><xmax>1474</xmax><ymax>215</ymax></bndbox></views><personid>617</personid><positionid>305250</positionid><views><viewnum>0</viewnum><bndbox><xmin>1675</xmin><ymin>211</ymin><xmax>1766</xmax><ymax>476</ymax></bndbox></views><personid>353</personid><positionid>243146</positionid><views><viewnum>0</viewnum><bndbox><xmin>853</xmin><ymin>199</ymin><xmax>927</xmax><ymax>479</ymax></bndbox></views><personid>177</personid><positionid>273419</positionid><views><viewnum>0</viewnum><bndbox><xmin>1070</xmin><ymin>190</ymin><xmax>1143</xmax><ymax>449</ymax></bndbox></views><personid>115</personid><positionid>326722</positionid><views><viewnum>0</viewnum><bndbox><xmin>1273</xmin><ymin>172</ymin><xmax>1340</xmax><ymax>392</ymax></bndbox></views><personid>563</personid><positionid>272904</positionid><views><viewnum>0</viewnum><bndbox><xmin>958</xmin><ymin>182</ymin><xmax>1026</xmax><ymax>433</ymax></bndbox></views><personid>592</personid><positionid>500615</positionid><views><viewnum>0</viewnum><bndbox><xmin>1785</xmin><ymin>143</ymin><xmax>1839</xmax><ymax>297</ymax></bndbox></views></annotation>